rbnotefield/__init__.py
rbnotefield/extension.py
rbnotefield-1.0.1.dist-info/DESCRIPTION.rst
rbnotefield-1.0.1.dist-info/METADATA
rbnotefield-1.0.1.dist-info/RECORD
rbnotefield-1.0.1.dist-info/WHEEL
rbnotefield-1.0.1.dist-info/entry_points.txt
rbnotefield-1.0.1.dist-info/metadata.json
rbnotefield-1.0.1.dist-info/top_level.txt
